{"is_source_file": true, "format": "Kotlin (Gradle Kotlin Script - .kts)", "description": "This file is a Gradle build script written in Kotlin for configuring plugins, repositories, and build settings for an Android project using Flutter.", "external_files": ["local.properties"], "external_methods": ["java.util.Properties()", "properties.load()", "require()"], "published": [], "classes": [], "methods": [], "calls": ["file()", "properties.load()", "properties.getProperty()", "require()"], "search-terms": ["gradle", "plugins", "flutter", "kotlin", "android", "settings.gradle.kts", "pluginManagement", "repositories", "includeBuild"], "state": 2, "file_id": 5, "knowledge_revision": 30, "git_revision": "9c780f117ca98adb83639fa2c45b85ebc4899cbe", "hash": "683f9ca2f32a701ed1517715bf394e23", "format-version": 4, "code-base-name": "frontend_flutter_app", "filename": "frontend_flutter_app/android/settings.gradle.kts", "revision_history": [{"30": "9c780f117ca98adb83639fa2c45b85ebc4899cbe"}]}